README.txt
setup.py
gimbiseo/__init__.py
gimbiseo/actions.py
gimbiseo/chinese.py
gimbiseo/chinese_cut.py
gimbiseo/commands.py
gimbiseo/demo.py
gimbiseo/dialogue.py
gimbiseo/error.py
gimbiseo/main.py
gimbiseo/qadict.py
gimbiseo/ui.py
gimbiseo/utils.py
gimbiseo/view.py
gimbiseo/window.py
gimbiseo.egg-info/PKG-INFO
gimbiseo.egg-info/SOURCES.txt
gimbiseo.egg-info/dependency_links.txt
gimbiseo.egg-info/top_level.txt
gimbiseo.egg-info/zip-safe